LICENSE
habitshare_api_python/__init__.py
habitshare_api_python/api.py
habitshare_api_python/api_async.py
habitshare_api_python/endpoints.py
habitshare_api_python-1.0.0.dist-info/LICENSE
habitshare_api_python-1.0.0.dist-info/WHEEL
habitshare_api_python-1.0.0.dist-info/METADATA
habitshare_api_python-1.0.0.dist-info/RECORD
