Metadata-Version: 2.1
Name: habitshare-api-python
Version: 1.0.0
Summary: Unofficial Python API client for HabitShare social habit tracking app.
License: MIT
Keywords: HabitShare,rest,api,python
Author: Cyrus Kirk
Author-email: cyrusjkirk@gmail.com
Requires-Python: >=3.10,<4.0
Classifier: Intended Audience :: Developers
Classifier: License :: OSI Approved :: MIT License
Classifier: Programming Language :: Python :: 3
Classifier: Programming Language :: Python :: 3.10
Classifier: Topic :: Software Development :: Libraries :: Python Modules
Requires-Dist: requests (>=2.28.1,<3.0.0)
